crx/Cogs.py
crx/Embed.py
crx/Invite.py
crx/Loguru.py
crx/Reader.py
crx/Restart.py
crx/Tortoise.py
crx/__init__.py
crx_utils-1.4.0.dist-info/METADATA
crx_utils-1.4.0.dist-info/WHEEL
crx_utils-1.4.0.dist-info/top_level.txt
crx_utils-1.4.0.dist-info/RECORD
