Metadata-Version: 2.1
Name: crx-utils
Version: 1.4.0
Summary: A collection of functions for creating Discord bots, works with nextcord.
Home-page: https://discord.gg/EEp67FWQDP
Author: CRX-DEV
Author-email: cherniq66@gmail.com
License: MIT License
Requires-Dist: tortoise-orm ==0.21.0
Requires-Dist: nextcord ==2.6.0
Requires-Dist: aiofiles ==23.2.1
Requires-Dist: fastenv ==0.5.0
Requires-Dist: loguru ==0.7.2
